{
  "VahidOOnLine": 244589,
  "mwarmonitor": 10571,
  "pm_afshaa": 93131,
  "iaghapour": 2666,
  "DEJradio": 5519,
  "mamlekate": 103654,
  "VahidOnline": 76114,
  "kianmeli1": 87827,
  "IranIntlTV": 341413,
  "FoxNewsChannel": 3,
  "Shin_Persian": 6802,
  "Iliaen": 4464,
  "CnnBrk": 247615,
  "reutersworldchannel": 151527,
  "ManotoTV": 105980,
  "FarsiVOA": 220176,
  "DW_Farsi": 125742,
  "Persian_Trend_Official": 16395,
  "RadioFarda": 158111,
  "IranianMinds": 22009,
  "BBCPersian": 283277,
  "IranWire": 65,
  "idfinfarsi": 11821,
  "Dirty_Kids": 391533,
  "Hranews": 113506,
  "officialrezapahlavi": 1841,
  "configx2ray": 38663,
  "manototv": 105980,
  "alonews": 126672,
  "farsi_fox_news": 89200,
  "FoxNewsTwitter": 342777,
  "CNNfarsiCHANNEL": 51273,
  "WithYashar": 14237
}