{
  "VahidOOnLine": 244540,
  "mwarmonitor": 10518,
  "pm_afshaa": 93013,
  "iaghapour": 2664,
  "DEJradio": 5510,
  "mamlekate": 103652,
  "VahidOnline": 76099,
  "kianmeli1": 87818,
  "IranIntlTV": 341356,
  "FoxNewsChannel": 3,
  "Shin_Persian": 6781,
  "Iliaen": 4462,
  "CnnBrk": 247615,
  "reutersworldchannel": 151527,
  "ManotoTV": 105980,
  "FarsiVOA": 220126,
  "DW_Farsi": 125729,
  "Persian_Trend_Official": 16271,
  "RadioFarda": 158100,
  "IranianMinds": 21923,
  "BBCPersian": 283259,
  "IranWire": 65,
  "idfinfarsi": 11820,
  "Dirty_Kids": 391472,
  "Hranews": 113497,
  "officialrezapahlavi": 1841,
  "configx2ray": 38663,
  "manototv": 105980,
  "alonews": 126557,
  "farsi_fox_news": 89200,
  "FoxNewsTwitter": 342761,
  "CNNfarsiCHANNEL": 51273,
  "WithYashar": 14127
}